livepeek/__init__.py
livepeek/cli.py
livepeek/fetcher.py
livepeek/utils.py
livepeek/viewer.py
livepeek-0.0.3.dist-info/licenses/LICENSE
livepeek-0.0.3.dist-info/METADATA
livepeek-0.0.3.dist-info/WHEEL
livepeek-0.0.3.dist-info/entry_points.txt
livepeek-0.0.3.dist-info/top_level.txt
livepeek-0.0.3.dist-info/RECORD
