Metadata-Version: 2.4
Name: livepeek
Version: 0.0.3
Summary: Live API response viewer in terminal
Author-email: Nuhman PK <nuhmanpk7@gmail.com>
License: GNU
Keywords: api,cli,json,terminal,developer-tools
Requires-Python: >=3.7
License-File: LICENSE
Requires-Dist: typer[all]
Requires-Dist: httpx
Requires-Dist: rich
Requires-Dist: click
Dynamic: license-file
